customErrorMessagesToSaveYourMentalHealth/__init__.py
customErrorMessagesToSaveYourMentalHealth/customizable_errors.py
customErrorMessagesToSaveYourMentalHealth/updated_dictionary_of_themes.py
customerrormessagestosaveyourmentalhealth-0.2.17.dist-info/licenses/LICENSE
customerrormessagestosaveyourmentalhealth-0.2.17.dist-info/METADATA
customerrormessagestosaveyourmentalhealth-0.2.17.dist-info/WHEEL
customerrormessagestosaveyourmentalhealth-0.2.17.dist-info/top_level.txt
customerrormessagestosaveyourmentalhealth-0.2.17.dist-info/RECORD
