Metadata-Version: 2.4
Name: customErrorMessagesToSaveYourMentalHealth
Version: 0.2.17
Summary: DONT KILL YOURSELF JUST YET, ENJOY ADDING EMOJIS AND WHATNOT TO YOUR ERROR MESSAGES
Author: Teo Richard
License: MIT
Classifier: Programming Language :: Python :: 3
Classifier: License :: OSI Approved :: MIT License
Requires-Python: >=3.6
License-File: LICENSE
Dynamic: author
Dynamic: classifier
Dynamic: description
Dynamic: description-content-type
Dynamic: license
Dynamic: license-file
Dynamic: requires-python
Dynamic: summary
